cipherowo/__init__.py
cipherowo-0.0.1.1.dist-info/LICENSE
cipherowo-0.0.1.1.dist-info/METADATA
cipherowo-0.0.1.1.dist-info/WHEEL
cipherowo-0.0.1.1.dist-info/top_level.txt
cipherowo-0.0.1.1.dist-info/RECORD
