Metadata-Version: 2.1
Name: cipherowo
Version: 0.0.1.1
Summary: A cool cipher package
Home-page: https://github.com/justamirror/cipherowo
Author: owo0212
Author-email: author@example.com
License: UNKNOWN
Project-URL: Bug Tracker, https://github.com/justamirror/cipherowo/issues
Platform: UNKNOWN
Classifier: Programming Language :: Python :: 3
Classifier: License :: OSI Approved :: MIT License
Classifier: Operating System :: OS Independent
Requires-Python: >=3.6
